{
  "distance_unit": "mm",
  "force_unit": "N",
  "nodes": [
    {
      "id": 103,
      "x": -1374.9969037320366,
      "y": 974.3492891393774,
      "z": -3.6095570976613087e-13
    },
    {
      "id": 104,
      "x": -659.6176847484456,
      "y": 984.98558905545,
      "z": -19.032936942589686
    },
    {
      "id": 108,
      "x": -1026.5626935588448,
      "y": 1600.3987814445572,
      "z": -3.1122788085278055
    },
    {
      "id": 115,
      "x": -650.8618899746773,
      "y": 1394.227497869243,
      "z": 569.0730158138142
    },
    {
      "id": 116,
      "x": -1366.8098394878907,
      "y": 1383.8066251394773,
      "z": 587.0564794425273
    },
    {
      "id": 120,
      "x": -998.9356026208853,
      "y": 770.9800226427793,
      "z": 575.8924730711052
    },
    {
      "id": 153,
      "x": -329.17456513622875,
      "y": 1599.4956078947355,
      "z": -14.36107175225848
    },
    {
      "id": 166,
      "x": 61.39055816920927,
      "y": 1409.3884236491706,
      "z": 548.4350606054453
    },
    {
      "id": 167,
      "x": -284.94013000243524,
      "y": 782.6821030222834,
      "z": 565.976670610633
    },
    {
      "id": 171,
      "x": 49.15271452566401,
      "y": 991.7514614253222,
      "z": -30.416243941890283
    },
    {
      "id": 203,
      "x": 366.2154697458208,
      "y": 1612.8937818368834,
      "z": -43.5466988630901
    },
    {
      "id": 216,
      "x": 761.8617053372329,
      "y": 1023.9419095471989,
      "z": -68.04759845960004
    },
    {
      "id": 217,
      "x": 767.818362642919,
      "y": 1436.2118608475232,
      "z": 517.6242136103344
    },
    {
      "id": 221,
      "x": 447.2238437634879,
      "y": 797.430224753674,
      "z": 531.397730594735
    },
    {
      "id": 313,
      "x": -667.274866297055,
      "y": 2084.9263967020547,
      "z": 379.12796146379054
    },
    {
      "id": 314,
      "x": -1383.1921490065959,
      "y": 2072.8369019659244,
      "z": 397.28710239947964
    },
    {
      "id": 318,
      "x": -1006.0137415160789,
      "y": 1871.8930904468382,
      "z": 970.3233730242
    },
    {
      "id": 350,
      "x": 40.36678588648695,
      "y": 2095.22404408821,
      "z": 351.40451026079654
    },
    {
      "id": 354,
      "x": -297.5192170043839,
      "y": 1889.885981904115,
      "z": 945.8021541639934
    },
    {
      "id": 384,
      "x": 731.3199440679045,
      "y": 2120.30727961017,
      "z": 308.16250931608954
    },
    {
      "id": 388,
      "x": 410.5763201462662,
      "y": 1916.244025086389,
      "z": 912.4148950586182
    }
  ],
  "edges": [
    {
      "id": 105,
      "n1": 103,
      "n2": 104
    },
    {
      "id": 109,
      "n1": 104,
      "n2": 108
    },
    {
      "id": 112,
      "n1": 108,
      "n2": 103
    },
    {
      "id": 117,
      "n1": 115,
      "n2": 116
    },
    {
      "id": 121,
      "n1": 116,
      "n2": 120
    },
    {
      "id": 124,
      "n1": 120,
      "n2": 115
    },
    {
      "id": 127,
      "n1": 116,
      "n2": 103
    },
    {
      "id": 130,
      "n1": 120,
      "n2": 103
    },
    {
      "id": 133,
      "n1": 115,
      "n2": 104
    },
    {
      "id": 136,
      "n1": 120,
      "n2": 104
    },
    {
      "id": 139,
      "n1": 116,
      "n2": 108
    },
    {
      "id": 142,
      "n1": 115,
      "n2": 108
    },
    {
      "id": 154,
      "n1": 115,
      "n2": 153
    },
    {
      "id": 157,
      "n1": 104,
      "n2": 153
    },
    {
      "id": 160,
      "n1": 108,
      "n2": 153
    },
    {
      "id": 168,
      "n1": 166,
      "n2": 167
    },
    {
      "id": 172,
      "n1": 167,
      "n2": 171
    },
    {
      "id": 175,
      "n1": 171,
      "n2": 166
    },
    {
      "id": 178,
      "n1": 167,
      "n2": 104
    },
    {
      "id": 181,
      "n1": 171,
      "n2": 104
    },
    {
      "id": 184,
      "n1": 166,
      "n2": 153
    },
    {
      "id": 187,
      "n1": 171,
      "n2": 153
    },
    {
      "id": 190,
      "n1": 167,
      "n2": 115
    },
    {
      "id": 193,
      "n1": 166,
      "n2": 115
    },
    {
      "id": 204,
      "n1": 166,
      "n2": 203
    },
    {
      "id": 207,
      "n1": 171,
      "n2": 203
    },
    {
      "id": 210,
      "n1": 153,
      "n2": 203
    },
    {
      "id": 218,
      "n1": 216,
      "n2": 217
    },
    {
      "id": 222,
      "n1": 217,
      "n2": 221
    },
    {
      "id": 225,
      "n1": 221,
      "n2": 216
    },
    {
      "id": 228,
      "n1": 217,
      "n2": 166
    },
    {
      "id": 231,
      "n1": 221,
      "n2": 166
    },
    {
      "id": 234,
      "n1": 216,
      "n2": 171
    },
    {
      "id": 237,
      "n1": 221,
      "n2": 171
    },
    {
      "id": 240,
      "n1": 217,
      "n2": 203
    },
    {
      "id": 243,
      "n1": 216,
      "n2": 203
    },
    {
      "id": 253,
      "n1": 167,
      "n2": 120
    },
    {
      "id": 258,
      "n1": 221,
      "n2": 167
    },
    {
      "id": 315,
      "n1": 313,
      "n2": 314
    },
    {
      "id": 319,
      "n1": 314,
      "n2": 318
    },
    {
      "id": 322,
      "n1": 318,
      "n2": 313
    },
    {
      "id": 325,
      "n1": 314,
      "n2": 116
    },
    {
      "id": 328,
      "n1": 318,
      "n2": 116
    },
    {
      "id": 331,
      "n1": 313,
      "n2": 115
    },
    {
      "id": 334,
      "n1": 318,
      "n2": 115
    },
    {
      "id": 337,
      "n1": 314,
      "n2": 108
    },
    {
      "id": 340,
      "n1": 313,
      "n2": 108
    },
    {
      "id": 351,
      "n1": 350,
      "n2": 313
    },
    {
      "id": 355,
      "n1": 313,
      "n2": 354
    },
    {
      "id": 358,
      "n1": 354,
      "n2": 350
    },
    {
      "id": 361,
      "n1": 354,
      "n2": 115
    },
    {
      "id": 364,
      "n1": 350,
      "n2": 166
    },
    {
      "id": 367,
      "n1": 354,
      "n2": 166
    },
    {
      "id": 370,
      "n1": 313,
      "n2": 153
    },
    {
      "id": 373,
      "n1": 350,
      "n2": 153
    },
    {
      "id": 385,
      "n1": 384,
      "n2": 350
    },
    {
      "id": 389,
      "n1": 350,
      "n2": 388
    },
    {
      "id": 392,
      "n1": 388,
      "n2": 384
    },
    {
      "id": 395,
      "n1": 388,
      "n2": 166
    },
    {
      "id": 398,
      "n1": 384,
      "n2": 217
    },
    {
      "id": 401,
      "n1": 388,
      "n2": 217
    },
    {
      "id": 404,
      "n1": 350,
      "n2": 203
    },
    {
      "id": 407,
      "n1": 384,
      "n2": 203
    },
    {
      "id": 418,
      "n1": 354,
      "n2": 318
    },
    {
      "id": 423,
      "n1": 354,
      "n2": 388
    }
  ],
  "standard_surface": [
    313,
    318,
    314
  ]
}